postgres_composite_types/__init__.py
postgres_composite_types/caster.py
postgres_composite_types/composite_type.py
postgres_composite_types/fields.py
postgres_composite_types/forms.py
postgres_composite_types/operations.py
postgres_composite_types/quoting.py
postgres_composite_types/signals.py
postgres_composite_types/templates/postgres_composite_types/forms/widgets/composite_type.html
django_postgres_composite_types-1.0.0b0.dist-info/METADATA
django_postgres_composite_types-1.0.0b0.dist-info/WHEEL
django_postgres_composite_types-1.0.0b0.dist-info/LICENSE
django_postgres_composite_types-1.0.0b0.dist-info/RECORD
