Metadata-Version: 2.1
Name: django-postgres-composite-types
Version: 1.0.0b0
Summary: Postgres composite types support for Django
License: BSD
Author: Danielle Madeley
Author-email: danielle@madeley.id.au
Requires-Python: >=3.7,<4.0
Classifier: License :: Other/Proprietary License
Classifier: Programming Language :: Python :: 3
Classifier: Programming Language :: Python :: 3.7
Classifier: Programming Language :: Python :: 3.8
Classifier: Programming Language :: Python :: 3.9
Classifier: Programming Language :: Python :: 3.10
Classifier: Programming Language :: Python :: 3.11
Requires-Dist: Django (>=3.2.16)
Requires-Dist: psycopg2 (>=2.8.4)
